README.rst
setup.py
reposmon/__init__.py
reposmon.egg-info/PKG-INFO
reposmon.egg-info/SOURCES.txt
reposmon.egg-info/dependency_links.txt
reposmon.egg-info/entry_points.txt
reposmon.egg-info/top_level.txt
reposmon.egg-info/zip-safe