Metadata-Version: 1.1
Name: reposmon
Version: 70
Summary: Monitor a git repository, execute a command when it changes. Basically a polling git-hook for pull.
Home-page: https://github.com/erikdejonge/reposmon
Author: Erik de Jonge
Author-email: erik@a8.nl
License: GPL
Platform: UNKNOWN
Classifier: Programming Language :: Python
Classifier: Programming Language :: Python :: 3
Classifier: Development Status :: 4 - Beta 
Classifier: Intended Audience :: Developers
Classifier: License :: OSI Approved :: GNU Library or Lesser General Public License (LGPL)
Classifier: Operating System :: POSIX
Classifier: Topic :: Software Development :: Quality Assurance
Classifier: Topic :: System
